pyrule34test/__init__.py
pyrule34test/async_rule34.py
pyrule34test/objects.py
pyrule34test-2.0.1.dist-info/METADATA
pyrule34test-2.0.1.dist-info/WHEEL
pyrule34test-2.0.1.dist-info/RECORD
