Metadata-Version: 2.1
Name: pyrule34test
Version: 2.0.1
Summary: Asynchronous wrapper for rule34.xxx.
Home-page: https://github.com/Hypick122/pyrule34
License: MIT
Keywords: async rule34,rule34 api,async,asyncio,wrapper,api
Author: Hypick122
Requires-Python: >=3.8,<4.0
Classifier: Intended Audience :: Developers
Classifier: License :: OSI Approved :: MIT License
Classifier: Programming Language :: Python :: 3
Classifier: Programming Language :: Python :: 3.8
Classifier: Programming Language :: Python :: 3.9
Classifier: Programming Language :: Python :: 3.10
Classifier: Programming Language :: Python :: 3.11
Classifier: Programming Language :: Python :: 3.12
Classifier: Programming Language :: Python :: 3.7
Classifier: Topic :: Software Development :: Libraries :: Python Modules
Classifier: Topic :: Software Development :: Quality Assurance
Classifier: Typing :: Typed
Requires-Dist: aiohttp (>=3.8.1,<4.0.0)
Requires-Dist: beautifulsoup4 (>=4.12.2,<5.0.0)
Requires-Dist: lxml (>=4.9.3,<5.0.0)
Project-URL: Bug Tracker, https://github.com/Hypick122/pyrule34/issues
Project-URL: Documentation, https://github.com/Hypick122/pyrule34/README.md
Project-URL: Repository, https://github.com/Hypick122/pyrule34
